{
    "globalStyle": {
        "navigationBarTitleText": "华玥组件库",
        "enablePullDownRefresh": false
    },
    "easycom": {
        "autoscan": true,
        "custom": {
            "^hy-(.*)": "hy-app/components/hy-$1/hy-$1.vue"
        }
    },
    "pages": [
        // GENERATED BY UNI-PAGES, PLATFORM: H5 || MP-WEIXIN
        {
            "path": "pages/index/Index",
            "type": "page",
            "style": {
                "navigationBarTitleText": "首页"
            }
        },
        {
            "path": "pages/mine/Index",
            "type": "page"
        },
        {
            "path": "pages/test/Index",
            "type": "page"
        }
    ],
    "subPackages": [
        {
            "root": "pages-design",
            "pages": [
                // GENERATED BY UNI-PAGES, PLATFORM: H5 || MP-WEIXIN
                {
                    "path": "a/a",
                    "type": "page",
                    "style": {
                        "h5": {
                            "titleNView": {
                                "buttons": [
                                    {
                                        "type": "share",
                                        "color": "#892FE8"
                                    }
                                ]
                            }
                        }
                    }
                },
                {
                    "path": "actionSheet/actionSheet",
                    "type": "page",
                    "style": {
                        "navigationBarTitleText": "操作菜单",
                        "h5": {
                            "titleNView": {
                                "buttons": [
                                    {
                                        "type": "share",
                                        "color": "#892FE8"
                                    }
                                ]
                            }
                        }
                    }
                },
                {
                    "path": "addressPicker/addressPicker",
                    "type": "page",
                    "style": {
                        "navigationBarTitleText": "地址选择器",
                        "h5": {
                            "titleNView": {
                                "buttons": [
                                    {
                                        "type": "share",
                                        "color": "#892FE8"
                                    }
                                ]
                            }
                        }
                    }
                },
                {
                    "path": "avatar/avatar",
                    "type": "page",
                    "style": {
                        "navigationBarTitleText": "头像",
                        "h5": {
                            "titleNView": {
                                "buttons": [
                                    {
                                        "type": "share",
                                        "color": "#892FE8"
                                    }
                                ]
                            }
                        }
                    }
                },
                {
                    "path": "backTop/backTop",
                    "type": "page",
                    "style": {
                        "navigationBarTitleText": "返回顶部",
                        "h5": {
                            "titleNView": {
                                "buttons": [
                                    {
                                        "type": "share",
                                        "color": "#892FE8"
                                    }
                                ]
                            }
                        }
                    }
                },
                {
                    "path": "badge/badge",
                    "type": "page",
                    "style": {
                        "navigationBarTitleText": "徽标数",
                        "h5": {
                            "titleNView": {
                                "buttons": [
                                    {
                                        "type": "share",
                                        "color": "#892FE8"
                                    }
                                ]
                            }
                        }
                    }
                },
                {
                    "path": "button/button",
                    "type": "page",
                    "style": {
                        "navigationBarTitleText": "按钮",
                        "h5": {
                            "titleNView": {
                                "buttons": [
                                    {
                                        "type": "share",
                                        "color": "#892FE8"
                                    }
                                ]
                            }
                        }
                    }
                },
                {
                    "path": "calendar/calendar",
                    "type": "page",
                    "style": {
                        "navigationBarTitleText": "日历",
                        "h5": {
                            "titleNView": {
                                "buttons": [
                                    {
                                        "type": "share",
                                        "color": "#892FE8"
                                    }
                                ]
                            }
                        }
                    }
                },
                {
                    "path": "card/card",
                    "type": "page",
                    "style": {
                        "navigationBarTitleText": "卡片",
                        "h5": {
                            "titleNView": {
                                "buttons": [
                                    {
                                        "type": "share",
                                        "color": "#892FE8"
                                    }
                                ]
                            }
                        }
                    }
                },
                {
                    "path": "cell/cell",
                    "type": "page",
                    "style": {
                        "navigationBarTitleText": "单元格",
                        "h5": {
                            "titleNView": {
                                "buttons": [
                                    {
                                        "type": "share",
                                        "color": "#892FE8"
                                    }
                                ]
                            }
                        }
                    }
                },
                {
                    "path": "checkbox/checkbox",
                    "type": "page",
                    "style": {
                        "navigationBarTitleText": "复选框",
                        "h5": {
                            "titleNView": {
                                "buttons": [
                                    {
                                        "type": "share",
                                        "color": "#892FE8"
                                    }
                                ]
                            }
                        }
                    }
                },
                {
                    "path": "checkButton/checkButton",
                    "type": "page",
                    "style": {
                        "navigationBarTitleText": "复选框按钮",
                        "h5": {
                            "titleNView": {
                                "buttons": [
                                    {
                                        "type": "share",
                                        "color": "#892FE8"
                                    }
                                ]
                            }
                        }
                    }
                },
                {
                    "path": "codeInput/codeInput",
                    "type": "page",
                    "style": {
                        "navigationBarTitleText": "验证码输入",
                        "h5": {
                            "titleNView": {
                                "buttons": [
                                    {
                                        "type": "share",
                                        "color": "#892FE8"
                                    }
                                ]
                            }
                        }
                    }
                },
                {
                    "path": "configProvider/configProvider",
                    "type": "page",
                    "style": {
                        "navigationBarTitleText": "全局配置",
                        "h5": {
                            "titleNView": {
                                "buttons": [
                                    {
                                        "type": "share",
                                        "color": "#892FE8"
                                    }
                                ]
                            }
                        }
                    }
                },
                {
                    "path": "countDown/countDown",
                    "type": "page",
                    "style": {
                        "navigationBarTitleText": "倒计时",
                        "h5": {
                            "titleNView": {
                                "buttons": [
                                    {
                                        "type": "share",
                                        "color": "#892FE8"
                                    }
                                ]
                            }
                        }
                    }
                },
                {
                    "path": "countTo/countTo",
                    "type": "page",
                    "style": {
                        "navigationBarTitleText": "数字滚动",
                        "h5": {
                            "titleNView": {
                                "buttons": [
                                    {
                                        "type": "share",
                                        "color": "#892FE8"
                                    }
                                ]
                            }
                        }
                    }
                },
                {
                    "path": "coupon/coupon",
                    "type": "page",
                    "style": {
                        "navigationBarTitleText": "优惠券",
                        "h5": {
                            "titleNView": {
                                "buttons": [
                                    {
                                        "type": "share",
                                        "color": "#892FE8"
                                    }
                                ]
                            }
                        }
                    }
                },
                {
                    "path": "datetimePicker/datetimePicker",
                    "type": "page",
                    "style": {
                        "navigationBarTitleText": "时间选择器",
                        "h5": {
                            "titleNView": {
                                "buttons": [
                                    {
                                        "type": "share",
                                        "color": "#892FE8"
                                    }
                                ]
                            }
                        }
                    }
                },
                {
                    "path": "divider/divider",
                    "type": "page",
                    "style": {
                        "navigationBarTitleText": "分割线",
                        "h5": {
                            "titleNView": {
                                "buttons": [
                                    {
                                        "type": "share",
                                        "color": "#892FE8"
                                    }
                                ]
                            }
                        }
                    }
                },
                {
                    "path": "dropdown/dropdown",
                    "type": "page",
                    "style": {
                        "navigationBarTitleText": "下拉菜单",
                        "h5": {
                            "titleNView": {
                                "buttons": [
                                    {
                                        "type": "share",
                                        "color": "#892FE8"
                                    }
                                ]
                            }
                        }
                    }
                },
                {
                    "path": "empty/empty",
                    "type": "page",
                    "style": {
                        "navigationBarTitleText": "空状态",
                        "h5": {
                            "titleNView": {
                                "buttons": [
                                    {
                                        "type": "share",
                                        "color": "#892FE8"
                                    }
                                ]
                            }
                        }
                    }
                },
                {
                    "path": "flex/flex",
                    "type": "page",
                    "style": {
                        "navigationBarTitleText": "弹性布局",
                        "h5": {
                            "titleNView": {
                                "buttons": [
                                    {
                                        "type": "share",
                                        "color": "#892FE8"
                                    }
                                ]
                            }
                        }
                    }
                },
                {
                    "path": "floatButton/floatButton",
                    "type": "page",
                    "style": {
                        "navigationBarTitleText": "悬浮按钮",
                        "h5": {
                            "titleNView": {
                                "buttons": [
                                    {
                                        "type": "share",
                                        "color": "#892FE8"
                                    }
                                ]
                            }
                        }
                    }
                },
                {
                    "path": "foldingPanel/foldingPanel",
                    "type": "page",
                    "style": {
                        "navigationBarTitleText": "折叠面板",
                        "h5": {
                            "titleNView": {
                                "buttons": [
                                    {
                                        "type": "share",
                                        "color": "#892FE8"
                                    }
                                ]
                            }
                        }
                    }
                },
                {
                    "path": "form/form",
                    "type": "page",
                    "style": {
                        "navigationBarTitleText": "表单",
                        "h5": {
                            "titleNView": {
                                "buttons": [
                                    {
                                        "type": "share",
                                        "color": "#892FE8"
                                    }
                                ]
                            }
                        }
                    }
                },
                {
                    "path": "formGroup/formGroup",
                    "type": "page",
                    "style": {
                        "navigationBarTitleText": "表单组",
                        "h5": {
                            "titleNView": {
                                "buttons": [
                                    {
                                        "type": "share",
                                        "color": "#892FE8"
                                    }
                                ]
                            }
                        }
                    }
                },
                {
                    "path": "grid/grid",
                    "type": "page",
                    "style": {
                        "navigationBarTitleText": "宫格布局",
                        "h5": {
                            "titleNView": {
                                "buttons": [
                                    {
                                        "type": "share",
                                        "color": "#892FE8"
                                    }
                                ]
                            }
                        }
                    }
                },
                {
                    "path": "icon/icon",
                    "type": "page",
                    "style": {
                        "navigationBarTitleText": "图标",
                        "h5": {
                            "titleNView": {
                                "buttons": [
                                    {
                                        "type": "share",
                                        "color": "#892FE8"
                                    }
                                ]
                            }
                        }
                    }
                },
                {
                    "path": "image/image",
                    "type": "page",
                    "style": {
                        "navigationBarTitleText": "图片",
                        "h5": {
                            "titleNView": {
                                "buttons": [
                                    {
                                        "type": "share",
                                        "color": "#892FE8"
                                    }
                                ]
                            }
                        }
                    }
                },
                {
                    "path": "indexBar/indexBar",
                    "type": "page",
                    "style": {
                        "navigationBarTitleText": "索引栏",
                        "h5": {
                            "titleNView": {
                                "buttons": [
                                    {
                                        "type": "share",
                                        "color": "#892FE8"
                                    }
                                ]
                            }
                        }
                    }
                },
                {
                    "path": "input/input",
                    "type": "page",
                    "style": {
                        "navigationBarTitleText": "输入框",
                        "h5": {
                            "titleNView": {
                                "buttons": [
                                    {
                                        "type": "share",
                                        "color": "#892FE8"
                                    }
                                ]
                            }
                        }
                    }
                },
                {
                    "path": "line/line",
                    "type": "page",
                    "style": {
                        "navigationBarTitleText": "线条",
                        "h5": {
                            "titleNView": {
                                "buttons": [
                                    {
                                        "type": "share",
                                        "color": "#892FE8"
                                    }
                                ]
                            }
                        }
                    }
                },
                {
                    "path": "lineProgress/lineProgress",
                    "type": "page",
                    "style": {
                        "navigationBarTitleText": "线形进度条",
                        "h5": {
                            "titleNView": {
                                "buttons": [
                                    {
                                        "type": "share",
                                        "color": "#892FE8"
                                    }
                                ]
                            }
                        }
                    }
                },
                {
                    "path": "list/list",
                    "type": "page",
                    "style": {
                        "navigationBarTitleText": "虚拟列表",
                        "h5": {
                            "titleNView": {
                                "buttons": [
                                    {
                                        "type": "share",
                                        "color": "#892FE8"
                                    }
                                ]
                            }
                        }
                    }
                },
                {
                    "path": "loading/loading",
                    "type": "page",
                    "style": {
                        "navigationBarTitleText": "加载中",
                        "h5": {
                            "titleNView": {
                                "buttons": [
                                    {
                                        "type": "share",
                                        "color": "#892FE8"
                                    }
                                ]
                            }
                        }
                    }
                },
                {
                    "path": "menu/menu",
                    "type": "page",
                    "style": {
                        "navigationBarTitleText": "侧边菜单栏",
                        "h5": {
                            "titleNView": {
                                "buttons": [
                                    {
                                        "type": "share",
                                        "color": "#892FE8"
                                    }
                                ]
                            }
                        }
                    }
                },
                {
                    "path": "modal/modal",
                    "type": "page",
                    "style": {
                        "navigationBarTitleText": "模态框",
                        "h5": {
                            "titleNView": {
                                "buttons": [
                                    {
                                        "type": "share",
                                        "color": "#892FE8"
                                    }
                                ]
                            }
                        }
                    }
                },
                {
                    "path": "navbar/navbar",
                    "type": "page",
                    "style": {
                        "navigationBarTitleText": "自定义导航栏",
                        "h5": {
                            "titleNView": {
                                "buttons": [
                                    {
                                        "type": "share",
                                        "color": "#892FE8"
                                    }
                                ]
                            }
                        }
                    }
                },
                {
                    "path": "noticeBar/noticeBar",
                    "type": "page",
                    "style": {
                        "navigationBarTitleText": "滚动通知",
                        "h5": {
                            "titleNView": {
                                "buttons": [
                                    {
                                        "type": "share",
                                        "color": "#892FE8"
                                    }
                                ]
                            }
                        }
                    }
                },
                {
                    "path": "notify/notify",
                    "type": "page",
                    "style": {
                        "navigationBarTitleText": "消息提示",
                        "h5": {
                            "titleNView": {
                                "buttons": [
                                    {
                                        "type": "share",
                                        "color": "#892FE8"
                                    }
                                ]
                            }
                        }
                    }
                },
                {
                    "path": "numberBox/numberBox",
                    "type": "page",
                    "style": {
                        "navigationBarTitleText": "步进器",
                        "h5": {
                            "titleNView": {
                                "buttons": [
                                    {
                                        "type": "share",
                                        "color": "#892FE8"
                                    }
                                ]
                            }
                        }
                    }
                },
                {
                    "path": "overlay/overlay",
                    "type": "page",
                    "style": {
                        "navigationBarTitleText": "遮罩层",
                        "h5": {
                            "titleNView": {
                                "buttons": [
                                    {
                                        "type": "share",
                                        "color": "#892FE8"
                                    }
                                ]
                            }
                        }
                    }
                },
                {
                    "path": "pagination/pagination",
                    "type": "page",
                    "style": {
                        "navigationBarTitleText": "分页",
                        "h5": {
                            "titleNView": {
                                "buttons": [
                                    {
                                        "type": "share",
                                        "color": "#892FE8"
                                    }
                                ]
                            }
                        }
                    }
                },
                {
                    "path": "parse/parse",
                    "type": "page",
                    "style": {
                        "navigationBarTitleText": "富文本",
                        "h5": {
                            "titleNView": {
                                "buttons": [
                                    {
                                        "type": "share",
                                        "color": "#892FE8"
                                    }
                                ]
                            }
                        }
                    }
                },
                {
                    "path": "picker/picker",
                    "type": "page",
                    "style": {
                        "navigationBarTitleText": "选择器",
                        "h5": {
                            "titleNView": {
                                "buttons": [
                                    {
                                        "type": "share",
                                        "color": "#892FE8"
                                    }
                                ]
                            }
                        }
                    }
                },
                {
                    "path": "popover/popover",
                    "type": "page",
                    "style": {
                        "navigationBarTitleText": "气泡",
                        "h5": {
                            "titleNView": {
                                "buttons": [
                                    {
                                        "type": "share",
                                        "color": "#892FE8"
                                    }
                                ]
                            }
                        }
                    }
                },
                {
                    "path": "popup/popup",
                    "type": "page",
                    "style": {
                        "navigationBarTitleText": "弹出层",
                        "h5": {
                            "titleNView": {
                                "buttons": [
                                    {
                                        "type": "share",
                                        "color": "#892FE8"
                                    }
                                ]
                            }
                        }
                    }
                },
                {
                    "path": "price/price",
                    "type": "page",
                    "style": {
                        "navigationBarTitleText": "金额",
                        "h5": {
                            "titleNView": {
                                "buttons": [
                                    {
                                        "type": "share",
                                        "color": "#892FE8"
                                    }
                                ]
                            }
                        }
                    }
                },
                {
                    "path": "qrcode/qrcode",
                    "type": "page",
                    "style": {
                        "navigationBarTitleText": "二维码",
                        "h5": {
                            "titleNView": {
                                "buttons": [
                                    {
                                        "type": "share",
                                        "color": "#892FE8"
                                    }
                                ]
                            }
                        }
                    }
                },
                {
                    "path": "radio/radio",
                    "type": "page",
                    "style": {
                        "navigationBarTitleText": "单选框",
                        "h5": {
                            "titleNView": {
                                "buttons": [
                                    {
                                        "type": "share",
                                        "color": "#892FE8"
                                    }
                                ]
                            }
                        }
                    }
                },
                {
                    "path": "rate/rate",
                    "type": "page",
                    "style": {
                        "navigationBarTitleText": "评分",
                        "h5": {
                            "titleNView": {
                                "buttons": [
                                    {
                                        "type": "share",
                                        "color": "#892FE8"
                                    }
                                ]
                            }
                        }
                    }
                },
                {
                    "path": "readMore/readMore",
                    "type": "page",
                    "style": {
                        "navigationBarTitleText": "展开阅读更多",
                        "h5": {
                            "titleNView": {
                                "buttons": [
                                    {
                                        "type": "share",
                                        "color": "#892FE8"
                                    }
                                ]
                            }
                        }
                    }
                },
                {
                    "path": "rollingNum/rollingNum",
                    "type": "page",
                    "style": {
                        "navigationBarTitleText": "翻滚数字",
                        "h5": {
                            "titleNView": {
                                "buttons": [
                                    {
                                        "type": "share",
                                        "color": "#892FE8"
                                    }
                                ]
                            }
                        }
                    }
                },
                {
                    "path": "scrollList/scrollList",
                    "type": "page",
                    "style": {
                        "navigationBarTitleText": "横向滚动列表",
                        "h5": {
                            "titleNView": {
                                "buttons": [
                                    {
                                        "type": "share",
                                        "color": "#892FE8"
                                    }
                                ]
                            }
                        }
                    }
                },
                {
                    "path": "search/search",
                    "type": "page",
                    "style": {
                        "navigationBarTitleText": "搜索",
                        "h5": {
                            "titleNView": {
                                "buttons": [
                                    {
                                        "type": "share",
                                        "color": "#892FE8"
                                    }
                                ]
                            }
                        }
                    }
                },
                {
                    "path": "signature/signature",
                    "type": "page",
                    "style": {
                        "navigationBarTitleText": "签名",
                        "h5": {
                            "titleNView": {
                                "buttons": [
                                    {
                                        "type": "share",
                                        "color": "#892FE8"
                                    }
                                ]
                            }
                        }
                    }
                },
                {
                    "path": "skeleton/skeleton",
                    "type": "page",
                    "style": {
                        "navigationBarTitleText": "骨架屏",
                        "h5": {
                            "titleNView": {
                                "buttons": [
                                    {
                                        "type": "share",
                                        "color": "#892FE8"
                                    }
                                ]
                            }
                        }
                    }
                },
                {
                    "path": "slider/slider",
                    "type": "page",
                    "style": {
                        "navigationBarTitleText": "滑动选择器",
                        "h5": {
                            "titleNView": {
                                "buttons": [
                                    {
                                        "type": "share",
                                        "color": "#892FE8"
                                    }
                                ]
                            }
                        }
                    }
                },
                {
                    "path": "steps/steps",
                    "type": "page",
                    "style": {
                        "navigationBarTitleText": "步骤条",
                        "h5": {
                            "titleNView": {
                                "buttons": [
                                    {
                                        "type": "share",
                                        "color": "#892FE8"
                                    }
                                ]
                            }
                        }
                    }
                },
                {
                    "path": "sticky/sticky",
                    "type": "page",
                    "style": {
                        "navigationBarTitleText": "吸顶",
                        "h5": {
                            "titleNView": {
                                "buttons": [
                                    {
                                        "type": "share",
                                        "color": "#892FE8"
                                    }
                                ]
                            }
                        }
                    }
                },
                {
                    "path": "submitBar/submitBar",
                    "type": "page",
                    "style": {
                        "navigationBarTitleText": "提交订单栏",
                        "h5": {
                            "titleNView": {
                                "buttons": [
                                    {
                                        "type": "share",
                                        "color": "#892FE8"
                                    }
                                ]
                            }
                        }
                    }
                },
                {
                    "path": "subsection/subsection",
                    "type": "page",
                    "style": {
                        "navigationBarTitleText": "分段器",
                        "h5": {
                            "titleNView": {
                                "buttons": [
                                    {
                                        "type": "share",
                                        "color": "#892FE8"
                                    }
                                ]
                            }
                        }
                    }
                },
                {
                    "path": "swipeAction/swipeAction",
                    "type": "page",
                    "style": {
                        "navigationBarTitleText": "滑动单元格",
                        "h5": {
                            "titleNView": {
                                "buttons": [
                                    {
                                        "type": "share",
                                        "color": "#892FE8"
                                    }
                                ]
                            }
                        }
                    }
                },
                {
                    "path": "swiper/swiper",
                    "type": "page",
                    "style": {
                        "navigationBarTitleText": "轮播图",
                        "h5": {
                            "titleNView": {
                                "buttons": [
                                    {
                                        "type": "share",
                                        "color": "#892FE8"
                                    }
                                ]
                            }
                        }
                    }
                },
                {
                    "path": "switch/switch",
                    "type": "page",
                    "style": {
                        "navigationBarTitleText": "开关选择器",
                        "h5": {
                            "titleNView": {
                                "buttons": [
                                    {
                                        "type": "share",
                                        "color": "#892FE8"
                                    }
                                ]
                            }
                        }
                    }
                },
                {
                    "path": "tabBar/tabBar",
                    "type": "page",
                    "style": {
                        "navigationBarTitleText": "底部导航栏",
                        "h5": {
                            "titleNView": {
                                "buttons": [
                                    {
                                        "type": "share",
                                        "color": "#892FE8"
                                    }
                                ]
                            }
                        }
                    }
                },
                {
                    "path": "table/table",
                    "type": "page",
                    "style": {
                        "navigationBarTitleText": "表格",
                        "h5": {
                            "titleNView": {
                                "buttons": [
                                    {
                                        "type": "share",
                                        "color": "#892FE8"
                                    }
                                ]
                            }
                        }
                    }
                },
                {
                    "path": "tabs/tabs",
                    "type": "page",
                    "style": {
                        "navigationBarTitleText": "标签页",
                        "h5": {
                            "titleNView": {
                                "buttons": [
                                    {
                                        "type": "share",
                                        "color": "#892FE8"
                                    }
                                ]
                            }
                        }
                    }
                },
                {
                    "path": "tag/tag",
                    "type": "page",
                    "style": {
                        "navigationBarTitleText": "标签",
                        "h5": {
                            "titleNView": {
                                "buttons": [
                                    {
                                        "type": "share",
                                        "color": "#892FE8"
                                    }
                                ]
                            }
                        }
                    }
                },
                {
                    "path": "text/text",
                    "type": "page",
                    "style": {
                        "navigationBarTitleText": "文本",
                        "h5": {
                            "titleNView": {
                                "buttons": [
                                    {
                                        "type": "share",
                                        "color": "#892FE8"
                                    }
                                ]
                            }
                        }
                    }
                },
                {
                    "path": "textarea/textarea",
                    "type": "page",
                    "style": {
                        "navigationBarTitleText": "文本域",
                        "h5": {
                            "titleNView": {
                                "buttons": [
                                    {
                                        "type": "share",
                                        "color": "#892FE8"
                                    }
                                ]
                            }
                        }
                    }
                },
                {
                    "path": "toast/toast",
                    "type": "page",
                    "style": {
                        "navigationBarTitleText": "消息提示",
                        "h5": {
                            "titleNView": {
                                "buttons": [
                                    {
                                        "type": "share",
                                        "color": "#892FE8"
                                    }
                                ]
                            }
                        }
                    }
                },
                {
                    "path": "tooltip/tooltip",
                    "type": "page",
                    "style": {
                        "navigationBarTitleText": "长按提示",
                        "h5": {
                            "titleNView": {
                                "buttons": [
                                    {
                                        "type": "share",
                                        "color": "#892FE8"
                                    }
                                ]
                            }
                        }
                    }
                },
                {
                    "path": "transition/transition",
                    "type": "page",
                    "style": {
                        "navigationBarTitleText": "动画",
                        "h5": {
                            "titleNView": {
                                "buttons": [
                                    {
                                        "type": "share",
                                        "color": "#892FE8"
                                    }
                                ]
                            }
                        }
                    }
                },
                {
                    "path": "upload/upload",
                    "type": "page",
                    "style": {
                        "navigationBarTitleText": "上传",
                        "h5": {
                            "titleNView": {
                                "buttons": [
                                    {
                                        "type": "share",
                                        "color": "#892FE8"
                                    }
                                ]
                            }
                        }
                    }
                },
                {
                    "path": "warn/warn",
                    "type": "page",
                    "style": {
                        "navigationBarTitleText": "警告提示",
                        "h5": {
                            "titleNView": {
                                "buttons": [
                                    {
                                        "type": "share",
                                        "color": "#892FE8"
                                    }
                                ]
                            }
                        }
                    }
                },
                {
                    "path": "waterfall/waterfall",
                    "type": "page",
                    "style": {
                        "navigationBarTitleText": "瀑布流",
                        "h5": {
                            "titleNView": {
                                "buttons": [
                                    {
                                        "type": "share",
                                        "color": "#892FE8"
                                    }
                                ]
                            }
                        }
                    }
                },
                {
                    "path": "watermark/watermark",
                    "type": "page",
                    "style": {
                        "navigationBarTitleText": "水印",
                        "h5": {
                            "titleNView": {
                                "buttons": [
                                    {
                                        "type": "share",
                                        "color": "#892FE8"
                                    }
                                ]
                            }
                        }
                    }
                }
            ]
        }
    ],
    "tabBar": {
        "color": "#7A7E83",
        "selectedColor": "#3cc51f",
        "borderStyle": "black",
        "list": [
            // GENERATED BY UNI-PAGES, PLATFORM: H5 || MP-WEIXIN
            {
                "pagePath": "pages/index/Index",
                "text": "首页",
                "iconPath": "./static/tabbar/home.png",
                "selectedIconPath": "./static/tabbar/homeHL.png"
            },
            {
                "pagePath": "pages/mine/Index",
                "text": "我的",
                "iconPath": "./static/tabbar/personal.png",
                "selectedIconPath": "./static/tabbar/personalHL.png"
            }
        ]
    }
}
